LICENSE
README.rst
pyproject.toml
setup.py
mid_to_gcode/__init__.py
mid_to_gcode/functions.py
mid_to_gcode/mid_to_gcod.py
mid_to_gcode/support_functions.py
mid_to_gcode.egg-info/PKG-INFO
mid_to_gcode.egg-info/SOURCES.txt
mid_to_gcode.egg-info/dependency_links.txt
mid_to_gcode.egg-info/top_level.txt